[
  {
    "inputs": [],
    "name": "Fee",
    "outputs": [
      {
        "internalType": "uint256",
        "name": "",
        "type": "uint256"
      }
    ],
    "stateMutability": "view",
    "type": "function"
  },
  {
    "inputs": [
      {
        "internalType": "string",
        "name": "",
        "type": "string"
      }
    ],
    "name": "appToCid",
    "outputs": [
      {
        "internalType": "string",
        "name": "",
        "type": "string"
      }
    ],
    "stateMutability": "view",
    "type": "function"
  },
  {
    "inputs": [
      {
        "internalType": "string",
        "name": "",
        "type": "string"
      },
      {
        "internalType": "uint256",
        "name": "",
        "type": "uint256"
      }
    ],
    "name": "appTypeToApps",
    "outputs": [
      {
        "internalType": "string",
        "name": "name",
        "type": "string"
      },
      {
        "internalType": "string",
        "name": "category",
        "type": "string"
      },
      {
        "internalType": "string",
        "name": "fileCid",
        "type": "string"
      },
      {
        "internalType": "string",
        "name": "iconCid",
        "type": "string"
      }
    ],
    "stateMutability": "view",
    "type": "function"
  },
  {
    "inputs": [],
    "name": "balance",
    "outputs": [
      {
        "internalType": "uint256",
        "name": "",
        "type": "uint256"
      }
    ],
    "stateMutability": "view",
    "type": "function"
  },
  {
    "inputs": [
      {
        "internalType": "address",
        "name": "",
        "type": "address"
      }
    ],
    "name": "developer",
    "outputs": [
      {
        "internalType": "bool",
        "name": "",
        "type": "bool"
      }
    ],
    "stateMutability": "view",
    "type": "function"
  },
  {
    "inputs": [],
    "name": "isDeveloper",
    "outputs": [
      {
        "internalType": "bool",
        "name": "",
        "type": "bool"
      }
    ],
    "stateMutability": "view",
    "type": "function"
  },
  {
    "inputs": [],
    "name": "pay",
    "outputs": [
      {
        "internalType": "uint256",
        "name": "",
        "type": "uint256"
      }
    ],
    "stateMutability": "payable",
    "type": "function"
  },
  {
    "inputs": [],
    "name": "getAllApps",
    "outputs": [
      {
        "components": [
          {
            "internalType": "string",
            "name": "name",
            "type": "string"
          },
          {
            "internalType": "string",
            "name": "category",
            "type": "string"
          },
          {
            "internalType": "string",
            "name": "fileCid",
            "type": "string"
          },
          {
            "internalType": "string",
            "name": "iconCid",
            "type": "string"
          }
        ],
        "internalType": "struct PlayStore.App[]",
        "name": "",
        "type": "tuple[]"
      }
    ],
    "stateMutability": "view",
    "type": "function"
  },
  {
    "inputs": [],
    "name": "getAllGames",
    "outputs": [
      {
        "components": [
          {
            "internalType": "string",
            "name": "name",
            "type": "string"
          },
          {
            "internalType": "string",
            "name": "category",
            "type": "string"
          },
          {
            "internalType": "string",
            "name": "fileCid",
            "type": "string"
          },
          {
            "internalType": "string",
            "name": "iconCid",
            "type": "string"
          }
        ],
        "internalType": "struct PlayStore.App[]",
        "name": "",
        "type": "tuple[]"
      }
    ],
    "stateMutability": "view",
    "type": "function"
  },
  {
    "inputs": [],
    "name": "getAllComics",
    "outputs": [
      {
        "components": [
          {
            "internalType": "string",
            "name": "name",
            "type": "string"
          },
          {
            "internalType": "string",
            "name": "category",
            "type": "string"
          },
          {
            "internalType": "string",
            "name": "fileCid",
            "type": "string"
          },
          {
            "internalType": "string",
            "name": "iconCid",
            "type": "string"
          }
        ],
        "internalType": "struct PlayStore.App[]",
        "name": "",
        "type": "tuple[]"
      }
    ],
    "stateMutability": "view",
    "type": "function"
  },
  {
    "inputs": [
      {
        "internalType": "string",
        "name": "_category",
        "type": "string"
      },
      {
        "internalType": "string",
        "name": "_appType",
        "type": "string"
      },
      {
        "internalType": "string",
        "name": "_appName",
        "type": "string"
      },
      {
        "internalType": "string",
        "name": "_fileCid",
        "type": "string"
      },
      {
        "internalType": "string",
        "name": "_iconCid",
        "type": "string"
      }
    ],
    "name": "create",
    "outputs": [
      {
        "internalType": "string",
        "name": "",
        "type": "string"
      }
    ],
    "stateMutability": "nonpayable",
    "type": "function"
  }
]